<?xml version="1.0" encoding="utf-8"?>
<odoo>
    <record id="internal_stock_location_website_form_inherit" model="ir.ui.view">
        <field name="name">internal.stock.location.website.form.inherit</field>
        <field name="model">stock.location</field>
        <field name="inherit_id" ref="stock.view_location_form"/>
        <field name="arch" type="xml">
            <xpath expr="//field[@name='usage']" position="after">
                <field name="stock_website"/>
            </xpath>
        </field>
    </record>
</odoo>